[
   {
      "count" : "51",
      "name" : "Saint Etienne",
      "position" : 1
   },
   {
      "count" : "48",
      "name" : "Alanis Morissette",
      "position" : 2
   },
   {
      "count" : "18",
      "name" : "Peter Gabriel",
      "position" : 3
   },
   {
      "count" : "16",
      "name" : "Spiritualized",
      "position" : 4
   },
   {
      "count" : "14",
      "name" : "Lorde",
      "position" : 5
   },
   {
      "count" : "8",
      "name" : "Paul Giovanni",
      "position" : 6
   },
   {
      "count" : "7",
      "name" : "LCD Soundsystem",
      "position" : 7
   },
   {
      "count" : "7",
      "name" : "The Police",
      "position" : 8
   },
   {
      "count" : "6",
      "name" : "Fleetwood Mac",
      "position" : 9
   },
   {
      "count" : "5",
      "name" : "Doves",
      "position" : 10
   }
]

